[
  {
    "id": "garden0",
    "name": "Garden Home",
    "slug": "garden"
  },
  {
    "id": "garden1",
    "name": "Layout 1",
    "slug": "layout-detail&layout=1"
  },
  {
    "id": "garden2",
    "name": "Layout 2",
    "slug": "layout-detail&layout=2"
  },
  {
    "id": "garden3",
    "name": "Layout 3",
    "slug": "layout-detail&layout=3"
  },
  {
    "id": "garden4",
    "name": "Layout 4",
    "slug": "layout-detail&layout=4"
  },
  {
    "id": "oldGarden",
    "class": "hover-hide",
    "name": "Old Garden",
    "slug": "projects/old-garden"
  }
]
